signature_mahalanobis_knn/__init__.py
signature_mahalanobis_knn/mahal_distance.py
signature_mahalanobis_knn/py.typed
signature_mahalanobis_knn/sig_mahal_knn.py
signature_mahalanobis_knn/utils.py
signature_mahalanobis_knn/baselines/isolation_forest.py
signature_mahalanobis_knn/baselines/local_outlier_factor.py
signature_mahalanobis_knn/baselines/utils.py
signature_mahalanobis_knn-0.1.0.dist-info/METADATA
signature_mahalanobis_knn-0.1.0.dist-info/WHEEL
signature_mahalanobis_knn-0.1.0.dist-info/licenses/LICENSE
signature_mahalanobis_knn-0.1.0.dist-info/RECORD
