Metadata-Version: 2.1
Name: signature_mahalanobis_knn
Version: 0.1.0
Summary: Using Nearest Neighbour-Variance Norm with Path Signatures for anomaly detection of streams
Project-URL: Homepage, https://github.com/datasig-ac-uk/signature_mahalanobis_knn
Project-URL: Bug Tracker, https://github.com/datasig-ac-uk/signature_mahalanobis_knn/issues
Project-URL: Discussions, https://github.com/datasig-ac-uk/signature_mahalanobis_knn/discussions
Project-URL: Changelog, https://github.com/datasig-ac-uk/signature_mahalanobis_knn/releases
Author-email: Zhen Shao <zhen.shao@maths.ox.ac.uk>, Ryan Chan <rchan@turing.ac.uk>
License-File: LICENSE
Classifier: Intended Audience :: Developers
Classifier: Intended Audience :: Science/Research
Classifier: License :: OSI Approved :: MIT License
Classifier: Operating System :: OS Independent
Classifier: Programming Language :: Python
Classifier: Programming Language :: Python :: 3
Classifier: Programming Language :: Python :: 3 :: Only
Classifier: Programming Language :: Python :: 3.8
Classifier: Programming Language :: Python :: 3.9
Classifier: Programming Language :: Python :: 3.10
Classifier: Programming Language :: Python :: 3.11
Classifier: Topic :: Scientific/Engineering
Classifier: Typing :: Typed
Requires-Python: <3.12,>=3.8
Requires-Dist: matplotlib
Requires-Dist: numba
Requires-Dist: numpy
Requires-Dist: pandas
Requires-Dist: pynndescent
Requires-Dist: scikit-learn
Requires-Dist: sktime>=0.24.1
Provides-Extra: dev
Requires-Dist: pytest-cov>=3; extra == 'dev'
Requires-Dist: pytest>=6; extra == 'dev'
Provides-Extra: docs
Requires-Dist: furo>=2023.08.17; extra == 'docs'
Requires-Dist: myst-parser>=0.13; extra == 'docs'
Requires-Dist: sphinx-autodoc-typehints; extra == 'docs'
Requires-Dist: sphinx-copybutton; extra == 'docs'
Requires-Dist: sphinx>=7.0; extra == 'docs'
Provides-Extra: signatures
Requires-Dist: esig; python_version < '3.10' and extra == 'signatures'
Provides-Extra: test
Requires-Dist: pytest-cov>=3; extra == 'test'
Requires-Dist: pytest>=6; extra == 'test'
